context_var
