Metadata-Version: 1.0
Name: context-var
Version: 0.1.1
Summary: React-style context variables
Home-page: http://github.com/willcrichton/context-var
Author: Will Crichton
Author-email: wcrichto@cs.stanford.edu
License: Apache 2.0
Platform: UNKNOWN
